chibi_django/__init__.py
chibi_django/apps.py
chibi_django/exceptions.py
chibi_django/fields.py
chibi_django/managers.py
chibi_django/mixins.py
chibi_django/models.py
chibi_django/pagination.py
chibi_django/serializers_fields.py
chibi_django/settings.py
chibi_django/urls.py
chibi_django/view_set.py
chibi_django/views.py
chibi_django/wsgi.py
chibi_django/migration/__init__.py
chibi_django/snippet/__init__.py
chibi_django/snippet/elasticsearch.py
chibi_django/snippet/query.py
chibi_django/snippet/url.py
chibi_django/tests/__init__.py
chibi_django/tests/integration/__init__.py
chibi_django/tests/integration/models.py
chibi_django/tests/integration/view_set.py
chibi_django/tests/unit/__init__.py
chibi_django/tests/unit/exceptions.py
chibi_django/tests/unit/models.py
chibi_django/tests/unit/snippets.py
chibi_django-0.5.1.dist-info/licenses/COPYING
chibi_user/__init__.py
chibi_user/admin.py
chibi_user/auth0_backend.py
chibi_user/authentication.py
chibi_user/managers.py
chibi_user/serializers.py
chibi_user/settings.py
chibi_user/urls.py
chibi_user/user_base.py
chibi_user/views.py
chibi_user/factories/__init__.py
chibi_user/factories/token.py
chibi_user/factories/user.py
chibi_user/jwt/__init__.py
chibi_user/middleware/__init__.py
chibi_user/middleware/metric.py
chibi_user/migrations/0001_initial.py
chibi_user/migrations/0002_auto_20211208_2045.py
chibi_user/migrations/0003_auto_20211210_2229.py
chibi_user/migrations/0004_auto_20220218_0025.py
chibi_user/migrations/__init__.py
chibi_user/models/__init__.py
chibi_user/models/group.py
chibi_user/models/mixin.py
chibi_user/models/permission.py
chibi_user/models/token.py
chibi_user/models/user.py
chibi_user/tests/__init__.py
chibi_user/tests/acceptance/__init__.py
chibi_user/tests/integration/__init__.py
chibi_user/tests/integration/authentication.py
chibi_user/tests/integration/manager.py
chibi_user/tests/integration/models.py
chibi_user/tests/integration/views.py
chibi_user/tests/integration/middleware/__init__.py
chibi_user/tests/integration/middleware/metric.py
chibi_django-0.5.1.dist-info/METADATA
chibi_django-0.5.1.dist-info/WHEEL
chibi_django-0.5.1.dist-info/top_level.txt
chibi_django-0.5.1.dist-info/RECORD
