Metadata-Version: 2.4
Name: chibi_django
Version: 0.5.1
Home-page: https://github.com/dem4ply/chibi_django
Author: 
Author-email: 
Classifier: Environment :: Console
Classifier: Intended Audience :: Developers
Classifier: Programming Language :: Python
License-File: COPYING
Requires-Dist: Django>=2.0.7
Requires-Dist: django-filter>=2.0.7
Requires-Dist: djangorestframework>=3.8.2
Requires-Dist: drf-nested-routers>=0.90.2
Requires-Dist: chibi>=0.7.7
Requires-Dist: chibi_donkey>=1.0.0
Requires-Dist: chibi_auth0>=0.1.0
Dynamic: classifier
Dynamic: home-page
Dynamic: license-file
Dynamic: requires-dist
